hierarc/__init__.py
hierarc/Diagnostics/__init__.py
hierarc/Diagnostics/blinding.py
hierarc/Diagnostics/goodness_of_fit.py
hierarc/LensPosterior/__init__.py
hierarc/LensPosterior/anisotropy_config.py
hierarc/LensPosterior/base_config.py
hierarc/LensPosterior/ddt_kin_constraints.py
hierarc/LensPosterior/ddt_kin_gauss_constraints.py
hierarc/LensPosterior/imaging_constraints.py
hierarc/LensPosterior/kin_constraints.py
hierarc/Likelihood/__init__.py
hierarc/Likelihood/anisotropy_scaling.py
hierarc/Likelihood/cosmo_likelihood.py
hierarc/Likelihood/hierarchy_likelihood.py
hierarc/Likelihood/lens_sample_likelihood.py
hierarc/Likelihood/transformed_cosmography.py
hierarc/Likelihood/KDELikelihood/__init__.py
hierarc/Likelihood/KDELikelihood/chain.py
hierarc/Likelihood/KDELikelihood/kde_likelihood.py
hierarc/Likelihood/LensLikelihood/__init__.py
hierarc/Likelihood/LensLikelihood/base_lens_likelihood.py
hierarc/Likelihood/LensLikelihood/ddt_dd_gauss_likelihood.py
hierarc/Likelihood/LensLikelihood/ddt_dd_kde_likelihood.py
hierarc/Likelihood/LensLikelihood/ddt_gauss_kin_likelihood.py
hierarc/Likelihood/LensLikelihood/ddt_gauss_likelihood.py
hierarc/Likelihood/LensLikelihood/ddt_hist_kin_likelihood.py
hierarc/Likelihood/LensLikelihood/ddt_hist_likelihood.py
hierarc/Likelihood/LensLikelihood/ddt_lognorm_likelihood.py
hierarc/Likelihood/LensLikelihood/double_source_plane.py
hierarc/Likelihood/LensLikelihood/ds_dds_gauss_likelihood.py
hierarc/Likelihood/LensLikelihood/kin_likelihood.py
hierarc/Likelihood/LensLikelihood/mag_likelihood.py
hierarc/Likelihood/LensLikelihood/td_mag_likelihood.py
hierarc/Likelihood/LensLikelihood/td_mag_magnitude_likelihood.py
hierarc/Likelihood/SneLikelihood/__init__.py
hierarc/Likelihood/SneLikelihood/sne_likelihood.py
hierarc/Likelihood/SneLikelihood/sne_likelihood_custom.py
hierarc/Likelihood/SneLikelihood/sne_likelihood_from_file.py
hierarc/Likelihood/SneLikelihood/sne_pantheon_plus.py
hierarc/Sampling/__init__.py
hierarc/Sampling/mcmc_sampling.py
hierarc-1.1.2.dist-info/AUTHORS.rst
hierarc-1.1.2.dist-info/LICENSE
hierarc-1.1.2.dist-info/METADATA
hierarc-1.1.2.dist-info/WHEEL
hierarc-1.1.2.dist-info/top_level.txt
hierarc-1.1.2.dist-info/RECORD
