Metadata-Version: 2.1
Name: hierarc
Version: 1.1.2
Summary: Hierarchical analysis of strong lensing systems to infer lens properties and cosmological parameters simultaneously
Home-page: https://github.com/sibirrer/hierarc
Author: Simon Birrer
Author-email: sibirrer@gmail.com
License: BSD license
Keywords: hierarc
Platform: UNKNOWN
Classifier: Development Status :: 5 - Production/Stable
Classifier: Intended Audience :: Developers
Classifier: License :: OSI Approved :: BSD License
Classifier: Natural Language :: English
Classifier: Programming Language :: Python :: 3
Classifier: Programming Language :: Python :: 3.6
Classifier: Programming Language :: Python :: 3.7
Classifier: Programming Language :: Python :: 3.8
Classifier: Programming Language :: Python :: 3.9
Requires-Python: >=3.8
License-File: LICENSE
License-File: AUTHORS.rst
Requires-Dist: numpy (>=1.13)
Requires-Dist: scipy (>=0.14.0)
